{
    "prepare_queue": {
        "installed": [],
        "uninstalled": []
    },
    "config_munge": {
        "files": {
            "res/xml/config.xml": {
                "parents": {
                    "/*": [
                        {
                            "xml": "<feature name=\"SocialMessage\"><param name=\"android-package\" value=\"uk.co.ilee.socialmessage.SocialMessage\" /></feature>",
                            "count": 1
                        },
                        {
                            "xml": "<feature name=\"SocialSharing\"><param name=\"android-package\" value=\"nl.xservices.plugins.SocialSharing\" /></feature>",
                            "count": 1
                        }
                    ]
                }
            },
            "AndroidManifest.xml": {
                "parents": {
                    "/*": [
                        {
                            "xml": "<uses-permission android:name=\"android.permission.WRITE_EXTERNAL_STORAGE\" />",
                            "count": 2
                        },
                        {
                            "xml": "<uses-permission android:name=\"android.permission.ACCESS_COARSE_LOCATION\" />",
                            "count": 1
                        },
                        {
                            "xml": "<uses-permission android:name=\"android.permission.ACCESS_FINE_LOCATION\" />",
                            "count": 1
                        }
                    ]
                }
            }
        }
    },
    "installed_plugins": {
        "cordova-plugin-social-message": {
            "PACKAGE_NAME": "io.cordova.SalesMarket"
        },
        "cordova-plugin-x-socialsharing": {
            "PACKAGE_NAME": "io.cordova.SalesMarket"
        },
        "org.apache.cordova.geolocation": {
            "PACKAGE_NAME": "io.cordova.SalesMarket"
        }
    },
    "dependent_plugins": {}
}